odoo8_addon_l10n_it_sepa_bonifici-8.0.1.0.1-nspkg.pth
odoo_addons/l10n_it_sepa_bonifici/README.rst
odoo_addons/l10n_it_sepa_bonifici/__init__.py
odoo_addons/l10n_it_sepa_bonifici/__openerp__.py
odoo_addons/l10n_it_sepa_bonifici/data/CBIBdyCrossBorderPaymentRequest.00.01.01.xsd
odoo_addons/l10n_it_sepa_bonifici/data/CBIBdyPaymentRequest.00.04.00.xsd
odoo_addons/l10n_it_sepa_bonifici/data/CBICrossBorderPaymentRequestLogMsg.00.01.01.xsd
odoo_addons/l10n_it_sepa_bonifici/data/CBICrossBorderPaymentRequestPhyMsg.00.01.01.xsd
odoo_addons/l10n_it_sepa_bonifici/data/CBIHdrSrv.001.07.xsd
odoo_addons/l10n_it_sepa_bonifici/data/CBIHdrTrt.001.07.xsd
odoo_addons/l10n_it_sepa_bonifici/data/CBIPaymentRequest.00.04.00.xsd
odoo_addons/l10n_it_sepa_bonifici/data/CBIPaymentRequestMsg.00.04.00.xsd
odoo_addons/l10n_it_sepa_bonifici/data/CBISgnInf.001.04.xsd
odoo_addons/l10n_it_sepa_bonifici/data/payment_type_sepa_cbi.xml
odoo_addons/l10n_it_sepa_bonifici/i18n/it.po
odoo_addons/l10n_it_sepa_bonifici/i18n/l10n_it_sepa_bonifici.pot
odoo_addons/l10n_it_sepa_bonifici/i18n/sl.po
odoo_addons/l10n_it_sepa_bonifici/static/company_setting.png
odoo_addons/l10n_it_sepa_bonifici/static/make_payment.png
odoo_addons/l10n_it_sepa_bonifici/static/make_payment_download.png
odoo_addons/l10n_it_sepa_bonifici/static/make_payment_wizard.png
odoo_addons/l10n_it_sepa_bonifici/static/order_payment.png
odoo_addons/l10n_it_sepa_bonifici/static/payment_mode1.png
odoo_addons/l10n_it_sepa_bonifici/static/payment_mode2.png
odoo_addons/l10n_it_sepa_bonifici/static/description/icon.png
odoo_addons/l10n_it_sepa_bonifici/wizard/__init__.py
odoo_addons/l10n_it_sepa_bonifici/wizard/export_sepa_cbi.py
odoo_addons/l10n_it_sepa_bonifici/wizard/export_sepa_cbi_estero.py
odoo_addons/l10n_it_sepa_bonifici/wizard/export_sepa_cbi_estero_view.xml
odoo_addons/l10n_it_sepa_bonifici/wizard/export_sepa_cbi_view.xml
odoo8_addon_l10n_it_sepa_bonifici-8.0.1.0.1.dist-info/METADATA
odoo8_addon_l10n_it_sepa_bonifici-8.0.1.0.1.dist-info/WHEEL
odoo8_addon_l10n_it_sepa_bonifici-8.0.1.0.1.dist-info/namespace_packages.txt
odoo8_addon_l10n_it_sepa_bonifici-8.0.1.0.1.dist-info/top_level.txt
odoo8_addon_l10n_it_sepa_bonifici-8.0.1.0.1.dist-info/RECORD
