Metadata-Version: 2.1
Name: odoo8-addon-l10n-it-sepa-bonifici
Version: 8.0.1.0.1
Summary: Banking SEPA Italian Credit Transfer CBI
Home-page: http://www.openforce.it
Author: Openforce di Alessandro Camilli, Odoo Community Association (OCA)
Author-email: support@odoo-community.org
License: AGPL-3
Platform: UNKNOWN
Classifier: Programming Language :: Python
Classifier: Framework :: Odoo
Classifier: License :: OSI Approved :: GNU Affero General Public License v3
Requires-Python: ~=2.7
Requires-Dist: odoo8-addon-account-banking-pain-base
Requires-Dist: odoo (<9.0a,>=8.0a)
